pyappcache/__init__.py
pyappcache/cache.py
pyappcache/compression.py
pyappcache/fs.py
pyappcache/keys.py
pyappcache/memcache.py
pyappcache/py.typed
pyappcache/redis.py
pyappcache/sqlite_lru.py
pyappcache/serialisation/__init__.py
pyappcache/serialisation/core.py
pyappcache/serialisation/pandas.py
pyappcache/util/__init__.py
pyappcache/util/requests.py
pyappcache-0.10.0.dist-info/COPYING
pyappcache-0.10.0.dist-info/METADATA
pyappcache-0.10.0.dist-info/WHEEL
pyappcache-0.10.0.dist-info/top_level.txt
pyappcache-0.10.0.dist-info/RECORD
