Metadata-Version: 2.1
Name: pyappcache
Version: 0.10.0
Home-page: https://github.com/calpaterson/pyappcache
Author: Cal Paterson
Author-email: cal@calpaterson.com
Project-URL: Documentation, https://pyappcache.readthedocs.io/en/latest/
Project-URL: Code, https://github.com/calpaterson/pyappcache
Project-URL: Issue tracker, https://github.com/calpaterson/pyappcache/issues
Classifier: Intended Audience :: Developers
Classifier: License :: OSI Approved :: GNU General Public License v3 (GPLv3)
Classifier: Programming Language :: Python :: 3
Classifier: Programming Language :: Python :: 3.10
Classifier: Programming Language :: Python :: 3.11
Classifier: Programming Language :: Python :: 3.12
Classifier: Programming Language :: Python :: 3.8
Classifier: Programming Language :: Python :: 3.9
Requires-Python: >=3.8
License-File: COPYING
Requires-Dist: typing-extensions
Requires-Dist: python-dateutil
Provides-Extra: dev
Requires-Dist: bpython (~=0.18) ; extra == 'dev'
Provides-Extra: memcache
Requires-Dist: pylibmc ; extra == 'memcache'
Provides-Extra: redis
Requires-Dist: redis (>=3) ; extra == 'redis'
Provides-Extra: tests
Requires-Dist: black (~=22.10.0) ; extra == 'tests'
Requires-Dist: cachecontrol ; extra == 'tests'
Requires-Dist: flask ; extra == 'tests'
Requires-Dist: mypy (==0.991) ; extra == 'tests'
Requires-Dist: pandas ; extra == 'tests'
Requires-Dist: pandas-stubs ; extra == 'tests'
Requires-Dist: pyarrow ; extra == 'tests'
Requires-Dist: pyflakes ; extra == 'tests'
Requires-Dist: pytest-cov ; extra == 'tests'
Requires-Dist: pytest (~=7.2.0) ; extra == 'tests'
Requires-Dist: requests ; extra == 'tests'
Requires-Dist: sphinx-autodoc-typehints (~=1.19.5) ; extra == 'tests'
Requires-Dist: sphinx (==5.3.0) ; extra == 'tests'
Requires-Dist: time-machine (~=2.13.0) ; extra == 'tests'
Requires-Dist: types-python-dateutil ; extra == 'tests'
Requires-Dist: types-redis ; extra == 'tests'
Requires-Dist: types-requests ; extra == 'tests'
Requires-Dist: wheel ; extra == 'tests'
Requires-Dist: pylibmc ; extra == 'tests'
Requires-Dist: redis (>=3) ; extra == 'tests'
